[{"frequency":"1050561","word":"le","type":"(d&eacute;t.)"},{"frequency":"862100","word":"de","type":"(pr&eacute;p.)"},{"frequency":"419564","word":"un","type":"(d&eacute;t.)"},{"frequency":"351960","word":"&ecirc;tre","type":"(verbe)"},{"frequency":"362093","word":"et","type":"(conj.)"},{"frequency":"293083","word":"&agrave;","type":"(pr&eacute;p.)"},{"frequency":"270395","word":"il","type":"(pron.)"},{"frequency":"248488","word":"avoir","type":"(verbe)"},{"frequency":"186755","word":"ne","type":"(adv.)"},{"frequency":"184186","word":"je","type":"(pron.)"},{"frequency":"181161","word":"son","type":"(d&eacute;t.)"},{"frequency":"176161","word":"que","type":"(conj.)"},{"frequency":"168684","word":"se","type":"(pron.)"},{"frequency":"148392","word":"qui","type":"(pron.)"},{"frequency":"141389","word":"ce","type":"(d&eacute;t.)"},{"frequency":"139185","word":"dans","type":"(pr&eacute;p.)"},{"frequency":"143565","word":"en","type":"(pr&eacute;p.)"},{"frequency":"127384","word":"du","type":"(d&eacute;t.)"},{"frequency":"126397","word":"elle","type":"(pron.)"},{"frequency":"123502","word":"au","type":"(d&eacute;t.)"},{"frequency":"119106","word":"de","type":"(d&eacute;t.)"},{"frequency":"107074","word":"ce","type":"(pron.)"},{"frequency":"105873","word":"le","type":"(pron.)"},{"frequency":"104779","word":"pour","type":"(pr&eacute;p.)"},{"frequency":"103083","word":"pas","type":"(adv.)"},{"frequency":"99412","word":"que","type":"(pron.)"},{"frequency":"89623","word":"vous","type":"(pron.)"},{"frequency":"82277","word":"par","type":"(pr&eacute;p.)"},{"frequency":"80180","word":"sur","type":"(pr&eacute;p.)"},{"frequency":"77608","word":"faire","type":"(verbe)"},{"frequency":"75499","word":"plus","type":"(adv.)"},{"frequency":"72134","word":"dire","type":"(verbe)"},{"frequency":"71086","word":"me","type":"(pron.)"},{"frequency":"70246","word":"on","type":"(pron.)"},{"frequency":"70121","word":"mon","type":"(d&eacute;t.)"},{"frequency":"65988","word":"lui","type":"(pron.)"},{"frequency":"62554","word":"nous","type":"(pron.)"},{"frequency":"59902","word":"comme","type":"(conj.)"},{"frequency":"57690","word":"mais","type":"(conj.)"},{"frequency":"55394","word":"pouvoir","type":"(verbe)"},{"frequency":"55081","word":"avec","type":"(pr&eacute;p.)"},{"frequency":"47221","word":"tout","type":"(adj.)"},{"frequency":"46031","word":"y","type":"(pron.)"},{"frequency":"41702","word":"aller","type":"(verbe)"},{"frequency":"39659","word":"voir","type":"(verbe)"},{"frequency":"38935","word":"en","type":"(pron.)"},{"frequency":"37171","word":"bien","type":"(adv.)"},{"frequency":"36089","word":"o&ugrave;","type":"(pron.)"},{"frequency":"35915","word":"sans","type":"(pr&eacute;p.)"},{"frequency":"35774","word":"tu","type":"(pron.)"},{"frequency":"34897","word":"ou","type":"(conj.)"},{"frequency":"33950","word":"leur","type":"(d&eacute;t.)"},{"frequency":"33202","word":"homme","type":"(subst.)"},{"frequency":"32024","word":"si","type":"(adv.)"},{"frequency":"30211","word":"deux","type":"(num&eacute;r.)"},{"frequency":"30082","word":"mari","type":"(subst.)"},{"frequency":"30053","word":"moi","type":"(pron.)"},{"frequency":"29435","word":"vouloir","type":"(verbe)"},{"frequency":"28542","word":"te","type":"(pron.)"},{"frequency":"26148","word":"femme","type":"(subst.)"},{"frequency":"26023","word":"venir","type":"(verbe)"},{"frequency":"25592","word":"quand","type":"(conj.)"},{"frequency":"25388","word":"grand","type":"(adj.)"},{"frequency":"24270","word":"celui","type":"(pron.)"},{"frequency":"24024","word":"si","type":"(conj.)"},{"frequency":"23883","word":"notre","type":"(d&eacute;t.)"},{"frequency":"22703","word":"devoir","type":"(verbe)"},{"frequency":"22695","word":"l&agrave;","type":"(adv.)"},{"frequency":"22232","word":"jour","type":"(subst.)"},{"frequency":"20489","word":"prendre","type":"(verbe)"},{"frequency":"19994","word":"m&ecirc;me","type":"(adv.)"},{"frequency":"19942","word":"votre","type":"(d&eacute;t.)"},{"frequency":"19915","word":"tout","type":"(adv.)"},{"frequency":"19379","word":"rien","type":"(pron.)"},{"frequency":"19008","word":"petit","type":"(adj.)"},{"frequency":"19176","word":"encore","type":"(adv.)"},{"frequency":"18311","word":"aussi","type":"(adv.)"},{"frequency":"17953","word":"quelque","type":"(d&eacute;t.)"},{"frequency":"17797","word":"dont","type":"(pron.)"},{"frequency":"17486","word":"tout","type":"(pron.)"},{"frequency":"17166","word":"mer","type":"(subst.)"},{"frequency":"16833","word":"trouver","type":"(verbe)"},{"frequency":"16795","word":"donner","type":"(verbe)"},{"frequency":"16785","word":"temps","type":"(subst.)"},{"frequency":"16494","word":"&ccedil;a","type":"(pron.)"},{"frequency":"16251","word":"peu","type":"(adv.)"},{"frequency":"16081","word":"m&ecirc;me","type":"(adj.)"},{"frequency":"16078","word":"falloir","type":"(verbe)"},{"frequency":"15944","word":"sous","type":"(pr&eacute;p.)"},{"frequency":"15814","word":"parler","type":"(verbe)"},{"frequency":"15639","word":"alors","type":"(adv.)"},{"frequency":"15540","word":"main","type":"(subst.)"},{"frequency":"15524","word":"chose","type":"(subst.)"},{"frequency":"15513","word":"ton","type":"(d&eacute;t.)"},{"frequency":"15339","word":"mettre","type":"(verbe)"},{"frequency":"15241","word":"vie","type":"(subst.)"},{"frequency":"15102","word":"savoir","type":"(verbe)"},{"frequency":"14981","word":"yeux","type":"(subst.)"},{"frequency":"14976","word":"passer","type":"(verbe)"},{"frequency":"14688","word":"autre","type":"(adj.)"},{"frequency":"14606","word":"apr&egrave;s","type":"(pr&eacute;p.)"},{"frequency":"14604","word":"regarder","type":"(verbe)"},{"frequency":"14336","word":"toujours","type":"(adv.)"},{"frequency":"14257","word":"puis","type":"(conj.)"},{"frequency":"14255","word":"jamais","type":"(adv.)"},{"frequency":"14253","word":"cela","type":"(pron.)"},{"frequency":"14138","word":"aimer","type":"(verbe)"},{"frequency":"14039","word":"non","type":"(adv.)"},{"frequency":"13940","word":"heure","type":"(subst.)"},{"frequency":"13881","word":"croire","type":"(verbe)"},{"frequency":"13798","word":"cent","type":"(num&eacute;r.)"},{"frequency":"13737","word":"monde","type":"(subst.)"},{"frequency":"13562","word":"donc","type":"(conj.)"},{"frequency":"13348","word":"enfant","type":"(subst.)"},{"frequency":"13191","word":"fois","type":"(subst.)"},{"frequency":"13104","word":"seul","type":"(adj.)"},{"frequency":"13063","word":"autre","type":"(pron.)"},{"frequency":"13684","word":"entre","type":"(pr&eacute;p.)"},{"frequency":"12781","word":"vers","type":"(pr&eacute;p.)"},{"frequency":"12698","word":"chez","type":"(pr&eacute;p.)"},{"frequency":"12597","word":"demander","type":"(verbe)"},{"frequency":"12593","word":"jeune","type":"(adj.)"},{"frequency":"12465","word":"jusque","type":"(pr&eacute;p.)"},{"frequency":"12432","word":"tr&egrave;s","type":"(adv.)"},{"frequency":"12274","word":"moment","type":"(subst.)"},{"frequency":"12155","word":"rester","type":"(verbe)"},{"frequency":"12063","word":"r&eacute;pondre","type":"(verbe)"},{"frequency":"12051","word":"tout","type":"(d&eacute;t.)"},{"frequency":"11999","word":"t&ecirc;te","type":"(subst.)"},{"frequency":"11854","word":"p&egrave;re","type":"(subst.)"},{"frequency":"11842","word":"fille","type":"(subst.)"},{"frequency":"11758","word":"mille","type":"(num&eacute;r.)"},{"frequency":"11731","word":"premier","type":"(adj.)"},{"frequency":"11695","word":"car","type":"(conj.)"},{"frequency":"12009","word":"entendre","type":"(verbe)"},{"frequency":"11640","word":"ni","type":"(conj.)"},{"frequency":"11483","word":"bon","type":"(adj.)"},{"frequency":"11372","word":"trois","type":"(num&eacute;r.)"},{"frequency":"11312","word":"c&oelig;ur","type":"(subst.)"},{"frequency":"11296","word":"ainsi","type":"(adv.)"},{"frequency":"11274","word":"an","type":"(subst.)"},{"frequency":"10970","word":"quatre","type":"(num&eacute;r.)"},{"frequency":"10941","word":"un","type":"(pron.)"},{"frequency":"10786","word":"terre","type":"(subst.)"},{"frequency":"10692","word":"contre","type":"(pr&eacute;p.)"},{"frequency":"10661","word":"dieu","type":"(subst.)"},{"frequency":"10489","word":"monsieur","type":"(subst.)"},{"frequency":"10469","word":"voix","type":"(subst.)"},{"frequency":"10358","word":"penser","type":"(verbe)"},{"frequency":"10343","word":"quel","type":"(adj.)"},{"frequency":"10288","word":"arriver","type":"(verbe)"},{"frequency":"10287","word":"maison","type":"(subst.)"},{"frequency":"9995","word":"devant","type":"(pr&eacute;p.)"},{"frequency":"9991","word":"coup","type":"(subst.)"},{"frequency":"9870","word":"beau","type":"(adj.)"},{"frequency":"9769","word":"conna&icirc;tre","type":"(verbe)"},{"frequency":"9759","word":"devenir","type":"(verbe)"},{"frequency":"9755","word":"air","type":"(subst.)"},{"frequency":"9752","word":"mot","type":"(subst.)"},{"frequency":"9694","word":"nuit","type":"(subst.)"},{"frequency":"9585","word":"sentir","type":"(verbe)"},{"frequency":"9603","word":"eau","type":"(subst.)"},{"frequency":"9515","word":"vieux","type":"(adj.)"},{"frequency":"9482","word":"sembler","type":"(verbe)"},{"frequency":"9472","word":"moins","type":"(adv.)"},{"frequency":"9312","word":"tenir","type":"(verbe)"},{"frequency":"9098","word":"ici","type":"(adv.)"},{"frequency":"9037","word":"comprendre","type":"(verbe)"},{"frequency":"9005","word":"oui","type":"(adv.)"},{"frequency":"9002","word":"rendre","type":"(verbe)"},{"frequency":"8997","word":"toi","type":"(pron.)"},{"frequency":"8920","word":"vingt","type":"(num&eacute;r.)"},{"frequency":"8907","word":"depuis","type":"(pr&eacute;p.)"},{"frequency":"8851","word":"attendre","type":"(verbe)"},{"frequency":"8768","word":"sortir","type":"(verbe)"},{"frequency":"8744","word":"ami","type":"(subst.)"},{"frequency":"8686","word":"trop","type":"(adv.)"},{"frequency":"8649","word":"porte","type":"(subst.)"},{"frequency":"8574","word":"lequel","type":"(pron.)"},{"frequency":"8419","word":"chaque","type":"(d&eacute;t.)"},{"frequency":"8283","word":"amour","type":"(subst.)"},{"frequency":"8202","word":"pendant","type":"(pr&eacute;p.)"},{"frequency":"8170","word":"d&eacute;j&agrave;","type":"(adv.)"},{"frequency":"8040","word":"pied","type":"(subst.)"},{"frequency":"7960","word":"tant","type":"(adv.)"},{"frequency":"7944","word":"gens","type":"(subst.)"},{"frequency":"7824","word":"parce que","type":"(conj.)"},{"frequency":"7795","word":"nom","type":"(subst.)"},{"frequency":"7625","word":"vivre","type":"(verbe)"},{"frequency":"7544","word":"reprendre","type":"(verbe)"},{"frequency":"7614","word":"entrer","type":"(verbe)"},{"frequency":"7499","word":"porter","type":"(verbe)"},{"frequency":"7451","word":"pays","type":"(subst.)"},{"frequency":"7433","word":"ciel","type":"(subst.)"},{"frequency":"7425","word":"avant","type":"(pr&eacute;p.)"},{"frequency":"7415","word":"fr&egrave;re","type":"(subst.)"},{"frequency":"7399","word":"regard","type":"(subst.)"},{"frequency":"7304","word":"chercher","type":"(verbe)"},{"frequency":"7255","word":"&acirc;me","type":"(subst.)"},{"frequency":"7245","word":"c&ocirc;t&eacute;","type":"(subst.)"},{"frequency":"7182","word":"mort","type":"(subst.)"},{"frequency":"7114","word":"revenir","type":"(verbe)"},{"frequency":"7038","word":"noir","type":"(adj.)"},{"frequency":"7024","word":"maintenant","type":"(adv.)"},{"frequency":"7019","word":"nouveau","type":"(adj.)"},{"frequency":"6983","word":"ville","type":"(subst.)"},{"frequency":"6923","word":"rue","type":"(subst.)"},{"frequency":"7126","word":"enfin","type":"(adv.)"},{"frequency":"6892","word":"appeler","type":"(verbe)"},{"frequency":"6877","word":"soir","type":"(subst.)"},{"frequency":"6835","word":"chambre","type":"(subst.)"},{"frequency":"6785","word":"mourir","type":"(verbe)"},{"frequency":"6751","word":"pas","type":"(subst.)"},{"frequency":"6726","word":"partir","type":"(verbe)"},{"frequency":"6723","word":"cinq","type":"(num&eacute;r.)"},{"frequency":"7031","word":"esprit","type":"(subst.)"},{"frequency":"6692","word":"soleil","type":"(subst.)"},{"frequency":"6650","word":"dernier","type":"(adj.)"},{"frequency":"6610","word":"jeter","type":"(verbe)"},{"frequency":"6609","word":"dix","type":"(num&eacute;r.)"},{"frequency":"6588","word":"roi","type":"(subst.)"},{"frequency":"6489","word":"&eacute;tat","type":"(subst.)"},{"frequency":"6425","word":"corps","type":"(subst.)"},{"frequency":"6399","word":"beaucoup","type":"(adv.)"},{"frequency":"6397","word":"suivre","type":"(verbe)"},{"frequency":"6304","word":"bras","type":"(subst.)"},{"frequency":"6256","word":"&eacute;crire","type":"(verbe)"},{"frequency":"6246","word":"blanc","type":"(adj.)"},{"frequency":"6195","word":"montrer","type":"(verbe)"},{"frequency":"6182","word":"tomber","type":"(verbe)"},{"frequency":"6178","word":"place","type":"(subst.)"},{"frequency":"6169","word":"ouvrir","type":"(verbe)"},{"frequency":"6138","word":"ah","type":"(interj)"},{"frequency":"6102","word":"parti","type":"(subst.)"},{"frequency":"6090","word":"assez","type":"(adv.)"},{"frequency":"6078","word":"leur","type":"(pron.)"},{"frequency":"6059","word":"cher","type":"(adj.)"},{"frequency":"6054","word":"voil&agrave;","type":"(pr&eacute;p.)"},{"frequency":"6004","word":"ann&eacute;e","type":"(subst.)"},{"frequency":"5996","word":"loin","type":"(adv.)"},{"frequency":"5961","word":"point","type":"(adv.)"},{"frequency":"5954","word":"visage","type":"(subst.)"},{"frequency":"5946","word":"bruit","type":"(subst.)"},{"frequency":"5946","word":"lettre","type":"(subst.)"},{"frequency":"5922","word":"franc","type":"(subst.)"},{"frequency":"5861","word":"fond","type":"(subst.)"},{"frequency":"5835","word":"force","type":"(subst.)"},{"frequency":"5812","word":"arr&ecirc;ter","type":"(verbe)"},{"frequency":"5786","word":"perdre","type":"(verbe)"},{"frequency":"5783","word":"commencer","type":"(verbe)"},{"frequency":"5779","word":"para&icirc;tre","type":"(verbe)"},{"frequency":"5774","word":"aucun","type":"(d&eacute;t.)"},{"frequency":"5747","word":"marcher","type":"(verbe)"},{"frequency":"5706","word":"milieu","type":"(subst.)"},{"frequency":"5702","word":"saint","type":"(subst.)"},{"frequency":"5686","word":"id&eacute;e","type":"(subst.)"},{"frequency":"5662","word":"presque","type":"(adv.)"},{"frequency":"5629","word":"ailleurs","type":"(adv.)"},{"frequency":"5623","word":"travail","type":"(subst.)"},{"frequency":"5622","word":"lumi&egrave;re","type":"(subst.)"},{"frequency":"5562","word":"long","type":"(adj.)"},{"frequency":"5544","word":"seulement","type":"(adv.)"},{"frequency":"5527","word":"mois","type":"(subst.)"},{"frequency":"5520","word":"fils","type":"(subst.)"},{"frequency":"5508","word":"neuf","type":"(num&eacute;r.)"},{"frequency":"5505","word":"tel","type":"(d&eacute;t.)"},{"frequency":"5494","word":"lever","type":"(verbe)"},{"frequency":"5481","word":"raison","type":"(subst.)"},{"frequency":"5829","word":"effet","type":"(subst.)"},{"frequency":"5470","word":"gouvernement","type":"(subst.)"},{"frequency":"5467","word":"permettre","type":"(verbe)"},{"frequency":"5434","word":"pauvre","type":"(adj.)"},{"frequency":"5417","word":"asseoir","type":"(verbe)"},{"frequency":"5416","word":"point","type":"(subst.)"},{"frequency":"5413","word":"plein","type":"(adj.)"},{"frequency":"5391","word":"personne","type":"(subst.)"},{"frequency":"5385","word":"vrai","type":"(adj.)"},{"frequency":"5349","word":"peuple","type":"(subst.)"},{"frequency":"5343","word":"fait","type":"(subst.)"},{"frequency":"5295","word":"parole","type":"(subst.)"},{"frequency":"5273","word":"guerre","type":"(subst.)"},{"frequency":"5258","word":"toute","type":"(adj.)"},{"frequency":"5216","word":"&eacute;couter","type":"(verbe)"},{"frequency":"5214","word":"pens&eacute;e","type":"(subst.)"},{"frequency":"5179","word":"affaire","type":"(subst.)"},{"frequency":"5152","word":"quoi","type":"(pron.)"},{"frequency":"5145","word":"matin","type":"(subst.)"},{"frequency":"5127","word":"pierre","type":"(subst.)"},{"frequency":"5088","word":"monter","type":"(verbe)"},{"frequency":"5087","word":"bas","type":"(adj.)"},{"frequency":"5002","word":"vent","type":"(subst.)"},{"frequency":"4977","word":"doute","type":"(subst.)"},{"frequency":"4969","word":"front","type":"(subst.)"},{"frequency":"4939","word":"ombre","type":"(subst.)"},{"frequency":"4932","word":"part","type":"(subst.)"},{"frequency":"4916","word":"ma&icirc;tre","type":"(subst.)"},{"frequency":"4915","word":"aujourd'hui","type":"(adv.)"},{"frequency":"4908","word":"besoin","type":"(subst.)"},{"frequency":"4908","word":"question","type":"(subst.)"},{"frequency":"4904","word":"apercevoir","type":"(verbe)"},{"frequency":"4891","word":"recevoir","type":"(verbe)"},{"frequency":"4881","word":"mieux","type":"(adv.)"},{"frequency":"4859","word":"peine","type":"(subst.)"},{"frequency":"4836","word":"tour","type":"(subst.)"},{"frequency":"4806","word":"servir","type":"(verbe)"},{"frequency":"4766","word":"oh","type":"(interj)"},{"frequency":"4764","word":"autour","type":"(adv.)"},{"frequency":"4731","word":"pr&egrave;s","type":"(pr&eacute;p.)"},{"frequency":"4709","word":"finir","type":"(verbe)"},{"frequency":"4705","word":"famille","type":"(subst.)"},{"frequency":"4700","word":"pourquoi","type":"(conj.)"},{"frequency":"4665","word":"souvent","type":"(adv.)"},{"frequency":"4662","word":"rire","type":"(verbe)"},{"frequency":"4657","word":"dessus","type":"(adv.)"},{"frequency":"4653","word":"madame","type":"(subst.)"},{"frequency":"4635","word":"sorte","type":"(subst.)"},{"frequency":"4618","word":"figure","type":"(subst.)"},{"frequency":"4595","word":"droit","type":"(subst.)"},{"frequency":"4574","word":"peur","type":"(subst.)"},{"frequency":"4571","word":"bout","type":"(subst.)"},{"frequency":"4554","word":"lieu","type":"(subst.)"},{"frequency":"4541","word":"silence","type":"(subst.)"},{"frequency":"4537","word":"gros","type":"(adj.)"},{"frequency":"4503","word":"chef","type":"(subst.)"},{"frequency":"4584","word":"eh","type":"(interj)"},{"frequency":"4463","word":"six","type":"(num&eacute;r.)"},{"frequency":"4460","word":"bois","type":"(subst.)"},{"frequency":"4457","word":"mari","type":"(subst.)"},{"frequency":"4451","word":"histoire","type":"(subst.)"},{"frequency":"4449","word":"crier","type":"(verbe)"},{"frequency":"4447","word":"jouer","type":"(verbe)"},{"frequency":"4429","word":"feu","type":"(subst.)"},{"frequency":"4371","word":"tourner","type":"(verbe)"},{"frequency":"4355","word":"doux","type":"(adj.)"},{"frequency":"4355","word":"longtemps","type":"(adv.)"},{"frequency":"4350","word":"fort","type":"(adv.)"},{"frequency":"4332","word":"heureux","type":"(adj.)"},{"frequency":"4324","word":"comme","type":"(adv.)"},{"frequency":"4272","word":"garder","type":"(verbe)"},{"frequency":"4271","word":"partie","type":"(subst.)"},{"frequency":"4236","word":"face","type":"(subst.)"},{"frequency":"4231","word":"mouvement","type":"(subst.)"},{"frequency":"4217","word":"fin","type":"(subst.)"},{"frequency":"4198","word":"reconna&icirc;tre","type":"(verb)"},{"frequency":"4180","word":"quitter","type":"(verbe)"},{"frequency":"4164","word":"personne","type":"(pron.)"},{"frequency":"4163","word":"comment","type":"(adv.)"},{"frequency":"4155","word":"route","type":"(subst.)"},{"frequency":"4141","word":"d&egrave;s","type":"(pr&eacute;p.)"},{"frequency":"4127","word":"manger","type":"(verbe)"},{"frequency":"4097","word":"livre","type":"(subst.)"},{"frequency":"4070","word":"arbre","type":"(subst.)"},{"frequency":"4059","word":"courir","type":"(verbe)"},{"frequency":"4058","word":"cas","type":"(subst.)"},{"frequency":"4052","word":"huit","type":"(num&eacute;r.)"},{"frequency":"4041","word":"lorsque","type":"(conj.)"},{"frequency":"4034","word":"mur","type":"(subst.)"},{"frequency":"4028","word":"ordre","type":"(subst.)"},{"frequency":"4022","word":"continuer","type":"(verbe)"},{"frequency":"3978","word":"bonheur","type":"(subst.)"},{"frequency":"3965","word":"oublier","type":"(verbe)"},{"frequency":"3955","word":"descendre","type":"(verbe)"},{"frequency":"3953","word":"haut","type":"(adj.)"},{"frequency":"3922","word":"int&eacute;r&ecirc;t","type":"(subst.)"},{"frequency":"3920","word":"cacher","type":"(verbe)"},{"frequency":"3910","word":"l'un","type":"(pron.)"},{"frequency":"3890","word":"chacun","type":"(pron.)"},{"frequency":"3878","word":"profond","type":"(adj.)"},{"frequency":"3876","word":"argent","type":"(subst.)"},{"frequency":"3856","word":"cause","type":"(subst.)"},{"frequency":"3841","word":"poser","type":"(verbe)"},{"frequency":"3834","word":"autant","type":"(adv.)"},{"frequency":"3994","word":"est","type":"(subst.)"},{"frequency":"3825","word":"travers","type":"(subst.)"},{"frequency":"3809","word":"grand","type":"(subst.)"},{"frequency":"3807","word":"instant","type":"(subst.)"},{"frequency":"3784","word":"fa&ccedil;on","type":"(subst.)"},{"frequency":"3783","word":"d'abord","type":"(adv.)"},{"frequency":"3783","word":"oeil","type":"(subst.)"},{"frequency":"3778","word":"tirer","type":"(verbe)"},{"frequency":"3763","word":"forme","type":"(subst.)"},{"frequency":"3757","word":"pr&eacute;senter","type":"(verbe)"},{"frequency":"3755","word":"ajouter","type":"(verbe)"},{"frequency":"3753","word":"agir","type":"(verbe)"},{"frequency":"3717","word":"retrouver","type":"(verbe)"},{"frequency":"3711","word":"chemin","type":"(subst.)"},{"frequency":"3704","word":"cheveu","type":"(subst.)"},{"frequency":"3671","word":"offrir","type":"(verbe)"},{"frequency":"3669","word":"surtout","type":"(adv.)"},{"frequency":"3667","word":"certain","type":"(d&eacute;t.)"},{"frequency":"3656","word":"plaisir","type":"(subst.)"},{"frequency":"3639","word":"suite","type":"(subst.)"},{"frequency":"3616","word":"apprendre","type":"(verbe)"},{"frequency":"3612","word":"malgr&eacute;","type":"(pr&eacute;p.)"},{"frequency":"3598","word":"tuer","type":"(verbe)"},{"frequency":"3576","word":"rouge","type":"(adj.)"},{"frequency":"3571","word":"sang","type":"(subst.)"},{"frequency":"3559","word":"retourner","type":"(verbe)"},{"frequency":"3556","word":"rencontrer","type":"(verbe)"},{"frequency":"3548","word":"sentiment","type":"(subst.)"},{"frequency":"3516","word":"fleur","type":"(subst.)"},{"frequency":"3508","word":"cependant","type":"(adv.)"},{"frequency":"3498","word":"service","type":"(subst.)"},{"frequency":"3480","word":"plusieurs","type":"(d&eacute;t.)"},{"frequency":"3472","word":"table","type":"(subst.)"},{"frequency":"3465","word":"vite","type":"(adv.)"},{"frequency":"3446","word":"paix","type":"(subst.)"},{"frequency":"3482","word":"envoyer","type":"(verbe)"},{"frequency":"3444","word":"moyen","type":"(subst.)"},{"frequency":"3438","word":"dormir","type":"(verbe)"},{"frequency":"3422","word":"pousser","type":"(verbe)"},{"frequency":"3410","word":"lit","type":"(subst.)"},{"frequency":"3393","word":"humain","type":"(adj.)"},{"frequency":"3387","word":"voiture","type":"(subst.)"},{"frequency":"3362","word":"rappeler","type":"(verbe)"},{"frequency":"3345","word":"&ecirc;tre","type":"(subst.)"},{"frequency":"3340","word":"lire","type":"(verbe)"},{"frequency":"3337","word":"g&eacute;n&eacute;ral","type":"(adj.)"},{"frequency":"3335","word":"nature","type":"(subst.)"},{"frequency":"3326","word":"or","type":"(subst.)"},{"frequency":"3309","word":"pouvoir","type":"(subst.)"},{"frequency":"3307","word":"nouveau","type":"(subst.)"},{"frequency":"3299","word":"fran&ccedil;ais","type":"(adj.)"},{"frequency":"3292","word":"joie","type":"(subst.)"},{"frequency":"3289","word":"sept","type":"(num&eacute;r.)"},{"frequency":"3281","word":"tard","type":"(adv.)"},{"frequency":"3272","word":"pr&eacute;sident","type":"(subst.)"},{"frequency":"3271","word":"pourtant","type":"(adv.)"},{"frequency":"3266","word":"bouche","type":"(subst.)"},{"frequency":"3258","word":"changer","type":"(verbe)"},{"frequency":"3256","word":"petit","type":"(subst.)"},{"frequency":"3250","word":"froid","type":"(adj.)"},{"frequency":"3248","word":"compter","type":"(verbe)"},{"frequency":"3245","word":"occuper","type":"(verbe)"},{"frequency":"3245","word":"sens","type":"(subst.)"},{"frequency":"3240","word":"cri","type":"(subst.)"},{"frequency":"3237","word":"cheval","type":"(subst.)"},{"frequency":"3236","word":"loi","type":"(subst.)"},{"frequency":"3234","word":"sombre","type":"(adj.)"},{"frequency":"3223","word":"ci","type":"(adv.)"},{"frequency":"3211","word":"s&ucirc;r","type":"(adj.)"},{"frequency":"3238","word":"esp&egrave;ce","type":"(subst.)"},{"frequency":"3191","word":"voici","type":"(pr&eacute;p.)"},{"frequency":"3190","word":"ancien","type":"(adj.)"},{"frequency":"3189","word":"tandis que","type":"(conj.)"},{"frequency":"3161","word":"frapper","type":"(verbe)"},{"frequency":"3145","word":"ministre","type":"(subst.)"},{"frequency":"3139","word":"puisque","type":"(conj.)"},{"frequency":"3134","word":"selon","type":"(pr&eacute;p.)"},{"frequency":"3133","word":"travailler","type":"(verbe)"},{"frequency":"3238","word":"expliquer","type":"(verbe)"},{"frequency":"3125","word":"propre","type":"(adj.)"},{"frequency":"3124","word":"obtenir","type":"(verbe)"},{"frequency":"3099","word":"rentrer","type":"(verbe)"},{"frequency":"3097","word":"mal","type":"(adv.)"},{"frequency":"3096","word":"pleurer","type":"(verbe)"},{"frequency":"3254","word":"essayer","type":"(verbe)"},{"frequency":"3079","word":"r&eacute;p&eacute;ter","type":"(verbe)"},{"frequency":"3079","word":"soci&eacute;t&eacute;","type":"(subst.)"},{"frequency":"3076","word":"parfois","type":"(adv.)"},{"frequency":"3071","word":"politique","type":"(subst.)"},{"frequency":"3063","word":"oreille","type":"(subst.)"},{"frequency":"3056","word":"payer","type":"(verbe)"},{"frequency":"3054","word":"politique","type":"(adj.)"},{"frequency":"3053","word":"apporter","type":"(verbe)"},{"frequency":"3046","word":"fen&ecirc;tre","type":"(subst.)"},{"frequency":"3019","word":"derri&egrave;re","type":"(pr&eacute;p.)"},{"frequency":"3013","word":"possible","type":"(adj.)"},{"frequency":"3010","word":"fortune","type":"(subst.)"},{"frequency":"3002","word":"compte","type":"(subst.)"},{"frequency":"2979","word":"champ","type":"(subst.)"},{"frequency":"2961","word":"manier","type":"(subst.)"},{"frequency":"2960","word":"vraiment","type":"(adv.)"},{"frequency":"2948","word":"immense","type":"(adj.)"},{"frequency":"2942","word":"action","type":"(subst.)"},{"frequency":"2937","word":"boire","type":"(verbe)"},{"frequency":"2929","word":"public","type":"(adj.)"},{"frequency":"2914","word":"gar&ccedil;on","type":"(subst.)"},{"frequency":"2914","word":"pareil","type":"(adj.)"},{"frequency":"2906","word":"bleu","type":"(adj.)"},{"frequency":"2904","word":"sourire","type":"(verbe)"},{"frequency":"2890","word":"couleur","type":"(subst.)"},{"frequency":"2889","word":"coucher","type":"(verbe)"},{"frequency":"2875","word":"papier","type":"(subst.)"},{"frequency":"2865","word":"d'autres","type":"(d&eacute;t.)"},{"frequency":"2861","word":"mal","type":"(subst.)"},{"frequency":"2851","word":"fort","type":"(adj.)"},{"frequency":"2839","word":"bient&ocirc;t","type":"(adv.)"},{"frequency":"2825","word":"causer","type":"(verbe)"},{"frequency":"2820","word":"pi&egrave;ce","type":"(subst.)"},{"frequency":"2818","word":"montagne","type":"(subst.)"},{"frequency":"2812","word":"sol","type":"(subst.)"},{"frequency":"2811","word":"&oelig;uvre","type":"(subst.)"},{"frequency":"2810","word":"partout","type":"(adv.)"},{"frequency":"2809","word":"trente","type":"(num&eacute;r.)"},{"frequency":"2944","word":"exister","type":"(verbe)"},{"frequency":"2797","word":"cours","type":"(subst.)"},{"frequency":"2794","word":"raconter","type":"(verbe)"},{"frequency":"2792","word":"serrer","type":"(verbe)"},{"frequency":"2792","word":"songer","type":"(verbe)"},{"frequency":"2790","word":"d&eacute;sir","type":"(subst.)"},{"frequency":"2787","word":"manquer","type":"(verbe)"},{"frequency":"2776","word":"cour","type":"(subst.)"},{"frequency":"2754","word":"nommer","type":"(verbe)"},{"frequency":"2753","word":"bord","type":"(subst.)"},{"frequency":"2749","word":"douleur","type":"(subst.)"},{"frequency":"2735","word":"conduire","type":"(verbe)"},{"frequency":"2732","word":"salle","type":"(subst.)"},{"frequency":"2729","word":"saisir","type":"(verbe)"},{"frequency":"2722","word":"premier","type":"(subst.)"},{"frequency":"2721","word":"comment","type":"(conj.)"},{"frequency":"2715","word":"projet","type":"(subst.)"},{"frequency":"2709","word":"demeurer","type":"(verbe)"},{"frequency":"2704","word":"simple","type":"(adj.)"},{"frequency":"2701","word":"&eacute;tude","type":"(subst.)"},{"frequency":"2700","word":"remettre","type":"(verbe)"},{"frequency":"2699","word":"journal","type":"(subst.)"},{"frequency":"2697","word":"geste","type":"(subst.)"},{"frequency":"2689","word":"dispara&icirc;tre","type":"(verb)"},{"frequency":"2678","word":"battre","type":"(verbe)"},{"frequency":"2670","word":"toucher","type":"(verbe)"},{"frequency":"2664","word":"situation","type":"(subst.)"},{"frequency":"2661","word":"oiseau","type":"(subst.)"},{"frequency":"2654","word":"n&eacute;cessaire","type":"(adj.)"},{"frequency":"2906","word":"exemple","type":"(subst.)"},{"frequency":"2647","word":"si&egrave;cle","type":"(subst.)"},{"frequency":"2645","word":"appara&icirc;tre","type":"(verbe)"},{"frequency":"2635","word":"souffrir","type":"(verbe)"},{"frequency":"2633","word":"million","type":"(subst.)"},{"frequency":"2616","word":"prix","type":"(subst.)"},{"frequency":"2612","word":"groupe","type":"(subst.)"},{"frequency":"2610","word":"centre","type":"(subst.)"},{"frequency":"2603","word":"malheur","type":"(subst.)"},{"frequency":"2602","word":"honneur","type":"(subst.)"},{"frequency":"2590","word":"fermer","type":"(verbe)"},{"frequency":"2585","word":"accepter","type":"(verbe)"},{"frequency":"2575","word":"garde","type":"(subst.)"},{"frequency":"2570","word":"mauvais","type":"(adj.)"},{"frequency":"2569","word":"tendre","type":"(verbe)"},{"frequency":"2555","word":"na&icirc;tre","type":"(verbe)"},{"frequency":"2554","word":"sauver","type":"(verbe)"},{"frequency":"2717","word":"entier","type":"(adj.)"},{"frequency":"2547","word":"parmi","type":"(pr&eacute;p.)"},{"frequency":"2547","word":"probl&egrave;me","type":"(subst.)"},{"frequency":"2546","word":"larme","type":"(subst.)"},{"frequency":"2544","word":"avancer","type":"(verbe)"},{"frequency":"2539","word":"chien","type":"(subst.)"},{"frequency":"2534","word":"peau","type":"(subst.)"},{"frequency":"2530","word":"reste","type":"(subst.)"},{"frequency":"2522","word":"traverser","type":"(verbe)"},{"frequency":"2517","word":"nombre","type":"(subst.)"},{"frequency":"2515","word":"debout","type":"(adv.)"},{"frequency":"2514","word":"mesure","type":"(subst.)"},{"frequency":"2510","word":"social","type":"(adj.)"},{"frequency":"2508","word":"souvenir","type":"(verbe)"},{"frequency":"2507","word":"article","type":"(subst.)"},{"frequency":"2502","word":"vue","type":"(subst.)"},{"frequency":"2491","word":"couvrir","type":"(verbe)"},{"frequency":"2490","word":"&acirc;ge","type":"(subst.)"},{"frequency":"2485","word":"gagner","type":"(verbe)"},{"frequency":"2483","word":"syst&egrave;me","type":"(subst.)"},{"frequency":"2482","word":"long","type":"(subst.)"},{"frequency":"2481","word":"former","type":"(verbe)"},{"frequency":"2477","word":"plaire","type":"(verbe)"},{"frequency":"2458","word":"embrasser","type":"(verbe)"},{"frequency":"2455","word":"r&ecirc;ve","type":"(subst.)"},{"frequency":"2454","word":"oser","type":"(verbe)"},{"frequency":"2452","word":"afin de","type":"(pr&eacute;p.)"},{"frequency":"2448","word":"passion","type":"(subst.)"},{"frequency":"2440","word":"auquel","type":"(pron.)"},{"frequency":"2426","word":"rapport","type":"(subst.)"},{"frequency":"2420","word":"refuser","type":"(verbe)"},{"frequency":"2416","word":"important","type":"(adj.)"},{"frequency":"2415","word":"d&eacute;cider","type":"(verbe)"},{"frequency":"2401","word":"produire","type":"(verbe)"},{"frequency":"2398","word":"soldat","type":"(subst.)"},{"frequency":"2397","word":"l&egrave;vre","type":"(subst.)"},{"frequency":"2397","word":"signe","type":"(subst.)"},{"frequency":"2390","word":"v&eacute;rit&eacute;","type":"(subst.)"},{"frequency":"2389","word":"charger","type":"(verbe)"},{"frequency":"2386","word":"mariage","type":"(subst.)"},{"frequency":"2385","word":"m&ecirc;ler","type":"(verbe)"},{"frequency":"2380","word":"certain","type":"(adj.)"},{"frequency":"2365","word":"plan","type":"(subst.)"},{"frequency":"2349","word":"cesser","type":"(verbe)"},{"frequency":"2349","word":"ressembler","type":"(verbe)"},{"frequency":"2348","word":"dos","type":"(subst.)"},{"frequency":"2341","word":"marche","type":"(subst.)"},{"frequency":"2334","word":"souvenir","type":"(subst.)"},{"frequency":"2333","word":"dame","type":"(subst.)"},{"frequency":"2332","word":"chanter","type":"(verbe)"},{"frequency":"2328","word":"plut&ocirc;t","type":"(adv.)"},{"frequency":"2318","word":"conseil","type":"(subst.)"},{"frequency":"2314","word":"sou","type":"(subst.)"},{"frequency":"2307","word":"triste","type":"(adj.)"},{"frequency":"2306","word":"coin","type":"(subst.)"},{"frequency":"2303","word":"jardin","type":"(subst.)"},{"frequency":"2301","word":"joli","type":"(adj.)"},{"frequency":"2297","word":"soit","type":"(conj.)"},{"frequency":"2427","word":"emp&ecirc;cher","type":"(verbe)"},{"frequency":"2289","word":"doigt","type":"(subst.)"},{"frequency":"2288","word":"objet","type":"(subst.)"},{"frequency":"2284","word":"fer","type":"(subst.)"},{"frequency":"2281","word":"lendemain","type":"(subst.)"},{"frequency":"2281","word":"lentement","type":"(adv.)"},{"frequency":"2280","word":"combien","type":"(adv.)"},{"frequency":"2272","word":"approcher","type":"(verbe)"},{"frequency":"2265","word":"prier","type":"(verbe)"},{"frequency":"2259","word":"train","type":"(subst.)"},{"frequency":"2371","word":"esp&eacute;rer","type":"(verbe)"},{"frequency":"2256","word":"papa","type":"(subst.)"},{"frequency":"2254","word":"diff&eacute;rent","type":"(adj.)"},{"frequency":"2252","word":"valeur","type":"(subst.)"},{"frequency":"2247","word":"jeu","type":"(subst.)"},{"frequency":"2240","word":"&eacute;chapper","type":"(verbe)"},{"frequency":"2239","word":"glisser","type":"(verbe)"},{"frequency":"2234","word":"secret","type":"(subst.)"},{"frequency":"2233","word":"haut","type":"(subst.)"},{"frequency":"2226","word":"vieillard","type":"(subst.)"},{"frequency":"2225","word":"briller","type":"(verbe)"},{"frequency":"2222","word":"docteur","type":"(subst.)"},{"frequency":"2218","word":"br&ucirc;ler","type":"(verbe)"},{"frequency":"2218","word":"terrible","type":"(adj.)"},{"frequency":"2214","word":"placer","type":"(verbe)"},{"frequency":"2213","word":"ton","type":"(subst.)"},{"frequency":"2204","word":"jambe","type":"(subst.)"},{"frequency":"2202","word":"juger","type":"(verbe)"},{"frequency":"2201","word":"suffire","type":"(verbe)"},{"frequency":"2194","word":"endroit","type":"(subst.)"},{"frequency":"2192","word":"minute","type":"(subst.)"},{"frequency":"2190","word":"atteindre","type":"(verbe)"},{"frequency":"2190","word":"nuage","type":"(subst.)"},{"frequency":"2187","word":"pr&eacute;sence","type":"(subst.)"},{"frequency":"2165","word":"fou","type":"(adj.)"},{"frequency":"2163","word":"&eacute;paule","type":"(subst.)"},{"frequency":"2158","word":"l&eacute;ger","type":"(adj.)"},{"frequency":"2155","word":"feuille","type":"(subst.)"},{"frequency":"2155","word":"libert&eacute;","type":"(subst.)"},{"frequency":"2149","word":"journ&eacute;e","type":"(subst.)"},{"frequency":"2147","word":"libre","type":"(adj.)"},{"frequency":"2146","word":"annoncer","type":"(verbe)"},{"frequency":"2143","word":"avenir","type":"(subst.)"},{"frequency":"2142","word":"sourire","type":"(subst.)"},{"frequency":"2141","word":"hier","type":"(adv.)"},{"frequency":"2136","word":"r&eacute;sultat","type":"(subst.)"},{"frequency":"2135","word":"&eacute;lever","type":"(verbe)"},{"frequency":"2134","word":"acheter","type":"(verbe)"},{"frequency":"2133","word":"mener","type":"(verbe)"},{"frequency":"2133","word":"pr&eacute;parer","type":"(verbe)"},{"frequency":"2131","word":"pourquoi","type":"(adv.)"},{"frequency":"2125","word":"h&ocirc;tel","type":"(subst.)"},{"frequency":"2124","word":"semaine","type":"(subst.)"},{"frequency":"2122","word":"for&ecirc;t","type":"(subst.)"},{"frequency":"2118","word":"assurer","type":"(verbe)"},{"frequency":"2118","word":"pur","type":"(adj.)"},{"frequency":"2116","word":"qualit&eacute;","type":"(subst.)"},{"frequency":"2108","word":"prince","type":"(subst.)"},{"frequency":"2101","word":"bien","type":"(subst.)"},{"frequency":"2100","word":"&eacute;galement","type":"(adv.)"},{"frequency":"2095","word":"deviner","type":"(verbe)"},{"frequency":"2093","word":"m&eacute;decin","type":"(subst.)"},{"frequency":"2092","word":"consid&eacute;rer","type":"(verbe)"},{"frequency":"2087","word":"volont&eacute;","type":"(subst.)"},{"frequency":"2086","word":"seigneur","type":"(subst.)"},{"frequency":"2468","word":"effort","type":"(subst.)"},{"frequency":"2083","word":"quelque","type":"(adv.)"},{"frequency":"2081","word":"vert","type":"(adj.)"},{"frequency":"2077","word":"art","type":"(subst.)"},{"frequency":"2077","word":"moindre","type":"(adj.)"},{"frequency":"2076","word":"demain","type":"(adv.)"},{"frequency":"2073","word":"quarante","type":"(num&eacute;r.)"},{"frequency":"2072","word":"cinquante","type":"(num&eacute;r.)"},{"frequency":"2070","word":"foule","type":"(subst.)"},{"frequency":"2069","word":"appartenir","type":"(verbe)"},{"frequency":"2068","word":"aussit&ocirc;t","type":"(adv.)"},{"frequency":"2068","word":"ligne","type":"(subst.)"},{"frequency":"2067","word":"repr&eacute;senter","type":"(verb)"},{"frequency":"2065","word":"tromper","type":"(verbe)"},{"frequency":"2061","word":"int&eacute;rieur","type":"(subst.)"},{"frequency":"2056","word":"vendre","type":"(verbe)"},{"frequency":"2054","word":"beaut&eacute;","type":"(subst.)"},{"frequency":"2048","word":"riche","type":"(adj.)"},{"frequency":"2047","word":"craindre","type":"(verbe)"},{"frequency":"2046","word":"&eacute;trange","type":"(adj.)"},{"frequency":"2035","word":"emporter","type":"(verbe)"},{"frequency":"2032","word":"ensuite","type":"(adv.)"},{"frequency":"2025","word":"soin","type":"(subst.)"},{"frequency":"2020","word":"naturel","type":"(adj.)"},{"frequency":"2017","word":"hasard","type":"(subst.)"},{"frequency":"2013","word":"puis","type":"(adv.)"},{"frequency":"2006","word":"condition","type":"(subst.)"},{"frequency":"2000","word":"quinze","type":"(num&eacute;r.)"},{"frequency":"1997","word":"classe","type":"(subst.)"},{"frequency":"1996","word":"voyage","type":"(subst.)"},{"frequency":"1955","word":"aupr&egrave;s","type":"(pr&eacute;p.)"},{"frequency":"1955","word":"pr&eacute;sent","type":"(subst.)"},{"frequency":"1953","word":"caract&egrave;re","type":"(subst.)"},{"frequency":"1952","word":"attention","type":"(subst.)"},{"frequency":"1952","word":"gris","type":"(adj.)"},{"frequency":"1940","word":"or","type":"(conj.)"},{"frequency":"1939","word":"rouler","type":"(verbe)"},{"frequency":"1934","word":"faible","type":"(adj.)"},{"frequency":"1931","word":"poss&eacute;der","type":"(verbe)"},{"frequency":"1925","word":"sc&egrave;ne","type":"(subst.)"},{"frequency":"1921","word":"difficile","type":"(adj.)"},{"frequency":"1921","word":"fran&ccedil;ais","type":"(subst.)"},{"frequency":"1921","word":"r&eacute;veiller","type":"(verbe)"},{"frequency":"1920","word":"foi","type":"(subst.)"},{"frequency":"1918","word":"aider","type":"(verbe)"},{"frequency":"1918","word":"d&eacute;couvrir","type":"(verbe)"},{"frequency":"1913","word":"odeur","type":"(subst.)"},{"frequency":"1912","word":"choisir","type":"(verbe)"},{"frequency":"1912","word":"musique","type":"(subst.)"},{"frequency":"1909","word":"oncle","type":"(subst.)"},{"frequency":"1906","word":"&eacute;v&eacute;nement","type":"(subst.)"},{"frequency":"1905","word":"prononcer","type":"(verbe)"},{"frequency":"1905","word":"village","type":"(subst.)"},{"frequency":"1904","word":"taire","type":"(verbe)"},{"frequency":"1903","word":"envie","type":"(subst.)"},{"frequency":"1902","word":"midi","type":"(subst.)"},{"frequency":"1953","word":"ensemble","type":"(adv.)"},{"frequency":"1990","word":"expression","type":"(subst)"},{"frequency":"1896","word":"herbe","type":"(subst.)"},{"frequency":"1896","word":"vieux","type":"(subst.)"},{"frequency":"1895","word":"pluie","type":"(subst.)"},{"frequency":"1894","word":"pr&egrave;s","type":"(adv.)"},{"frequency":"1892","word":"bas","type":"(subst.)"},{"frequency":"1886","word":"r&ecirc;ver","type":"(verbe)"},{"frequency":"1884","word":"appuyer","type":"(verbe)"},{"frequency":"1884","word":"&eacute;tendre","type":"(verbe)"},{"frequency":"1882","word":"apr&egrave;s","type":"(adv.)"},{"frequency":"1882","word":"g&eacute;n&eacute;ral","type":"(subst.)"},{"frequency":"1880","word":"lutte","type":"(subst.)"},{"frequency":"1880","word":"trembler","type":"(verbe)"},{"frequency":"1877","word":"r&eacute;ponse","type":"(subst.)"},{"frequency":"1873","word":"gr&acirc;ce","type":"(subst.)"},{"frequency":"1872","word":"espace","type":"(subst.)"},{"frequency":"1866","word":"habitude","type":"(subst.)"},{"frequency":"1864","word":"d&eacute;fendre","type":"(verbe)"},{"frequency":"1861","word":"m&eacute;moire","type":"(subst.)"},{"frequency":"1856","word":"cr&eacute;er","type":"(verbe)"},{"frequency":"1856","word":"grave","type":"(adj.)"},{"frequency":"1853","word":"maintenir","type":"(verbe)"},{"frequency":"1845","word":"verre","type":"(subst.)"},{"frequency":"1840","word":"campagne","type":"(subst.)"},{"frequency":"1838","word":"quelqu'un","type":"(pron.)"},{"frequency":"1832","word":"juge","type":"(subst.)"},{"frequency":"1827","word":"genou","type":"(subst.)"},{"frequency":"1818","word":"impossible","type":"(adj.)"},{"frequency":"1816","word":"f&ecirc;te","type":"(subst.)"},{"frequency":"1814","word":"indiquer","type":"(verbe)"},{"frequency":"1813","word":"pr&ecirc;t","type":"(adj.)"},{"frequency":"1812","word":"promettre","type":"(verbe)"},{"frequency":"1810","word":"relever","type":"(verbe)"},{"frequency":"1809","word":"abandonner","type":"(verbe)"},{"frequency":"1797","word":"ignorer","type":"(verbe)"},{"frequency":"1792","word":"large","type":"(adj.)"},{"frequency":"1792","word":"parent","type":"(subst.)"},{"frequency":"1790","word":"col&egrave;re","type":"(subst.)"},{"frequency":"1951","word":"exprimer","type":"(verbe)"},{"frequency":"1788","word":"&eacute;toile","type":"(subst.)"},{"frequency":"1787","word":"devoir","type":"(subst.)"},{"frequency":"1784","word":"conscience","type":"(subst)"},{"frequency":"1861","word":"existence","type":"(subst.)"},{"frequency":"1769","word":"accompagner","type":"(verb)"},{"frequency":"1769","word":"immobile","type":"(adj.)"},{"frequency":"1763","word":"adresser","type":"(verbe)"},{"frequency":"1757","word":"observer","type":"(verbe)"},{"frequency":"1756","word":"juste","type":"(adj.)"},{"frequency":"1756","word":"puissance","type":"(subst.)"},{"frequency":"1755","word":"mati&egrave;re","type":"(subst.)"},{"frequency":"1754","word":"sable","type":"(subst.)"},{"frequency":"1753","word":"s&eacute;parer","type":"(verbe)"},{"frequency":"1752","word":"marier","type":"(verbe)"},{"frequency":"1751","word":"pr&eacute;voir","type":"(verbe)"},{"frequency":"1751","word":"vivant","type":"(adj.)"},{"frequency":"1746","word":"accord","type":"(subst.)"},{"frequency":"1745","word":"hiver","type":"(subst.)"},{"frequency":"1744","word":"retour","type":"(subst.)"},{"frequency":"1740","word":"autrefois","type":"(adv.)"},{"frequency":"1736","word":"genre","type":"(subst.)"},{"frequency":"1734","word":"d'autres","type":"(pron.)"},{"frequency":"1733","word":"vif","type":"(adj.)"},{"frequency":"1731","word":"amener","type":"(verbe)"},{"frequency":"1729","word":"obliger","type":"(verbe)"},{"frequency":"1725","word":"acte","type":"(subst.)"},{"frequency":"1724","word":"image","type":"(subst.)"},{"frequency":"1722","word":"horizon","type":"(subst.)"},{"frequency":"1720","word":"&eacute;clairer","type":"(verbe)"},{"frequency":"1719","word":"poursuivre","type":"(verbe)"},{"frequency":"1717","word":"danger","type":"(subst.)"},{"frequency":"1717","word":"livrer","type":"(verbe)"},{"frequency":"1716","word":"r&ocirc;le","type":"(subst.)"},{"frequency":"1711","word":"escalier","type":"(subst.)"},{"frequency":"1708","word":"go&ucirc;t","type":"(subst.)"},{"frequency":"1706","word":"b&ecirc;te","type":"(subst.)"},{"frequency":"1706","word":"ceci","type":"(pron.)"},{"frequency":"1705","word":"recherche","type":"(subst.)"},{"frequency":"1704","word":"membre","type":"(subst.)"},{"frequency":"1700","word":"pain","type":"(subst.)"},{"frequency":"1697","word":"phrase","type":"(subst.)"},{"frequency":"1696","word":"contenir","type":"(verbe)"},{"frequency":"1692","word":"rire","type":"(subst.)"},{"frequency":"1688","word":"fuir","type":"(verbe)"},{"frequency":"1687","word":"couler","type":"(verbe)"},{"frequency":"1687","word":"terme","type":"(subst.)"},{"frequency":"1680","word":"eaux","type":"(subst.)"},{"frequency":"1679","word":"moyen","type":"(adj.)"},{"frequency":"1678","word":"police","type":"(subst.)"},{"frequency":"1678","word":"rocher","type":"(subst.)"},{"frequency":"1676","word":"proposer","type":"(verbe)"},{"frequency":"1676","word":"tranquille","type":"(adj.)"},{"frequency":"1675","word":"unique","type":"(adj.)"},{"frequency":"1673","word":"&eacute;prouver","type":"(verbe)"},{"frequency":"1667","word":"retenir","type":"(verbe)"},{"frequency":"1667","word":"type","type":"(subst.)"},{"frequency":"1656","word":"vin","type":"(subst.)"},{"frequency":"1649","word":"sup&eacute;rieur","type":"(adj.)"},{"frequency":"1645","word":"attacher","type":"(verbe)"},{"frequency":"1642","word":"voler","type":"(verbe)"},{"frequency":"1638","word":"sec","type":"(adj.)"},{"frequency":"1636","word":"justice","type":"(subst.)"},{"frequency":"1635","word":"&eacute;poque","type":"(subst.)"},{"frequency":"1635","word":"passage","type":"(subst.)"},{"frequency":"1635","word":"somme","type":"(subst.)"},{"frequency":"1634","word":"science","type":"(subst.)"},{"frequency":"1633","word":"surprendre","type":"(verbe)"},{"frequency":"1626","word":"c&ocirc;te","type":"(subst.)"},{"frequency":"1620","word":"doucement","type":"(adv.)"},{"frequency":"1617","word":"gauche","type":"(subst.)"},{"frequency":"1613","word":"faute","type":"(subst.)"},{"frequency":"1612","word":"&eacute;cole","type":"(subst.)"},{"frequency":"1603","word":"bon","type":"(subst.)"},{"frequency":"1603","word":"ensemble","type":"(subst.)"},{"frequency":"1602","word":"rayon","type":"(subst.)"},{"frequency":"1601","word":"briser","type":"(verbe)"},{"frequency":"1598","word":"sujet","type":"(subst.)"},{"frequency":"1596","word":"imaginer","type":"(verbe)"},{"frequency":"1593","word":"diriger","type":"(verbe)"},{"frequency":"1591","word":"douze","type":"(num&eacute;r.)"},{"frequency":"1680","word":"en","type":"(adv.)"},{"frequency":"1587","word":"l'une","type":"(pron.)"},{"frequency":"1585","word":"dernier","type":"(subst.)"},{"frequency":"1582","word":"avis","type":"(subst.)"},{"frequency":"1581","word":"parvenir","type":"(verbe)"},{"frequency":"1578","word":"ouvert","type":"(adj.)"},{"frequency":"1574","word":"p&eacute;n&eacute;trer","type":"(verbe)"},{"frequency":"1573","word":"po&egrave;te","type":"(subst.)"},{"frequency":"1571","word":"meilleur","type":"(adj.)"},{"frequency":"1570","word":"paysan","type":"(subst.)"},{"frequency":"1569","word":"remarquer","type":"(verbe)"},{"frequency":"1568","word":"chair","type":"(subst.)"},{"frequency":"1568","word":"&eacute;viter","type":"(verbe)"},{"frequency":"1568","word":"soudain","type":"(adv.)"},{"frequency":"1561","word":"succ&egrave;s","type":"(subst.)"},{"frequency":"1558","word":"&icirc;le","type":"(subst.)"},{"frequency":"1556","word":"&eacute;tablir","type":"(verbe)"},{"frequency":"1553","word":"r&eacute;ussir","type":"(verbe)"},{"frequency":"1550","word":"pencher","type":"(verbe)"},{"frequency":"1547","word":"habiter","type":"(verbe)"},{"frequency":"1546","word":"entourer","type":"(verbe)"},{"frequency":"1544","word":"d&eacute;clarer","type":"(verbe)"},{"frequency":"1544","word":"d&eacute;tail","type":"(subst.)"},{"frequency":"1543","word":"arme","type":"(subst.)"},{"frequency":"1543","word":"r&eacute;alit&eacute;","type":"(subst.)"},{"frequency":"1539","word":"confiance","type":"(subst.)"},{"frequency":"1539","word":"masse","type":"(subst.)"},{"frequency":"1537","word":"crise","type":"(subst.)"},{"frequency":"1535","word":"&eacute;tonner","type":"(verbe)"},{"frequency":"1535","word":"poste","type":"(subst.)"},{"frequency":"1528","word":"dresser","type":"(verbe)"},{"frequency":"1528","word":"durer","type":"(verbe)"},{"frequency":"1527","word":"depuis","type":"(adv.)"},{"frequency":"1527","word":"faux","type":"(adj.)"},{"frequency":"1527","word":"fixer","type":"(verbe)"},{"frequency":"1526","word":"&eacute;norme","type":"(adj.)"},{"frequency":"1524","word":"principe","type":"(subst.)"},{"frequency":"1517","word":"direction","type":"(subst.)"},{"frequency":"1514","word":"taille","type":"(subst.)"},{"frequency":"1512","word":"d&eacute;sirer","type":"(verbe)"},{"frequency":"1512","word":"sant&eacute;","type":"(subst.)"},{"frequency":"1511","word":"ventre","type":"(subst.)"},{"frequency":"1508","word":"march&eacute;","type":"(subst.)"},{"frequency":"1506","word":"puissant","type":"(adj.)"},{"frequency":"1505","word":"simplement","type":"(adv.)"},{"frequency":"1504","word":"environ","type":"(adv.)"},{"frequency":"1504","word":"tellement","type":"(adv.)"},{"frequency":"1503","word":"arracher","type":"(verbe)"},{"frequency":"1636","word":"entra&icirc;ner","type":"(verbe)"},{"frequency":"1501","word":"soutenir","type":"(verbe)"},{"frequency":"1499","word":"couper","type":"(verbe)"},{"frequency":"1498","word":"trou","type":"(subst.)"},{"frequency":"1497","word":"inconnu","type":"(adj.)"},{"frequency":"1495","word":"pont","type":"(subst.)"},{"frequency":"1494","word":"lune","type":"(subst.)"},{"frequency":"1491","word":"dehors","type":"(adv.)"},{"frequency":"1490","word":"certes","type":"(adv.)"},{"frequency":"1489","word":"beaux","type":"(adj.)"},{"frequency":"1489","word":"robe","type":"(subst.)"},{"frequency":"1488","word":"douter","type":"(verbe)"},{"frequency":"1487","word":"retirer","type":"(verbe)"},{"frequency":"1486","word":"cesse","type":"(subst.)"},{"frequency":"1485","word":"brusquement","type":"(adv.)"},{"frequency":"1507","word":"entr&eacute;e","type":"(subst.)"},{"frequency":"1482","word":"source","type":"(subst.)"},{"frequency":"1471","word":"camarade","type":"(subst.)"},{"frequency":"1470","word":"dent","type":"(subst.)"},{"frequency":"1470","word":"quant &agrave;","type":"(pr&eacute;p.)"},{"frequency":"1469","word":"connaissance","type":"(subst.)"},{"frequency":"1469","word":"cou","type":"(subst.)"},{"frequency":"1466","word":"but","type":"(subst.)"},{"frequency":"1460","word":"promener","type":"(verbe)"},{"frequency":"1460","word":"vague","type":"(subst.)"},{"frequency":"1459","word":"&eacute;l&eacute;ment","type":"(subst.)"},{"frequency":"1457","word":"fil","type":"(subst.)"},{"frequency":"1457","word":"voie","type":"(subst.)"},{"frequency":"1453","word":"nez","type":"(subst.)"},{"frequency":"1447","word":"forcer","type":"(verbe)"},{"frequency":"1446","word":"particulier","type":"(adj.)"},{"frequency":"1443","word":"discours","type":"(subst.)"},{"frequency":"1443","word":"maladie","type":"(subst.)"},{"frequency":"1442","word":"chaleur","type":"(subst.)"},{"frequency":"1440","word":"gloire","type":"(subst.)"},{"frequency":"1438","word":"vide","type":"(adj.)"},{"frequency":"1497","word":"examiner","type":"(verbe)"},{"frequency":"1436","word":"revoir","type":"(verbe)"},{"frequency":"1434","word":"aide","type":"(subst.)"},{"frequency":"1432","word":"d&eacute;but","type":"(subst.)"},{"frequency":"1432","word":"ennemi","type":"(subst.)"},{"frequency":"1431","word":"second","type":"(adj.)"},{"frequency":"1426","word":"aile","type":"(subst.)"},{"frequency":"1426","word":"flamme","type":"(subst.)"},{"frequency":"1422","word":"chaise","type":"(subst.)"},{"frequency":"1422","word":"lourd","type":"(adj.)"},{"frequency":"1422","word":"sein","type":"(subst.)"},{"frequency":"1422","word":"v&eacute;ritable","type":"(adj.)"},{"frequency":"1421","word":"toit","type":"(subst.)"},{"frequency":"1420","word":"remplir","type":"(verbe)"},{"frequency":"1419","word":"terminer","type":"(verbe)"},{"frequency":"1419","word":"vaste","type":"(adj.)"},{"frequency":"1418","word":"nu","type":"(adj.)"},{"frequency":"1413","word":"poussi&egrave;re","type":"(subst.)"},{"frequency":"1411","word":"nord","type":"(subst.)"},{"frequency":"1397","word":"tenter","type":"(verbe)"},{"frequency":"1393","word":"&eacute;motion","type":"(subst.)"},{"frequency":"1390","word":"hors","type":"(pr&eacute;p.)"},{"frequency":"1390","word":"un","type":"(num&eacute;r.)"},{"frequency":"1389","word":"remonter","type":"(verbe)"},{"frequency":"1388","word":"r&eacute;volution","type":"(subst)"},{"frequency":"1388","word":"th&eacute;&acirc;tre","type":"(subst.)"},{"frequency":"1386","word":"arm&eacute;e","type":"(subst.)"},{"frequency":"1386","word":"court","type":"(adj.)"},{"frequency":"1385","word":"noir","type":"(subst.)"},{"frequency":"1384","word":"appartement","type":"(subs)"},{"frequency":"1384","word":"semblable","type":"(adj.)"},{"frequency":"1383","word":"installer","type":"(verbe)"},{"frequency":"1382","word":"haine","type":"(subst.)"},{"frequency":"1382","word":"jeune","type":"(subst.)"},{"frequency":"1381","word":"position","type":"(subst.)"},{"frequency":"1381","word":"seconde","type":"(subst.)"},{"frequency":"1379","word":"frais","type":"(adj.)"},{"frequency":"1378","word":"appel","type":"(subst.)"},{"frequency":"1375","word":"soulever","type":"(verbe)"},{"frequency":"1475","word":"espoir","type":"(subst.)"},{"frequency":"1373","word":"allumer","type":"(verbe)"},{"frequency":"1373","word":"imposer","type":"(verbe)"},{"frequency":"1372","word":"avant","type":"(adv.)"},{"frequency":"1371","word":"respirer","type":"(verbe)"},{"frequency":"1370","word":"arri&egrave;re","type":"(subst.)"},{"frequency":"1370","word":"baisser","type":"(verbe)"},{"frequency":"1370","word":"droite","type":"(subst.)"},{"frequency":"1370","word":"poitrine","type":"(subst.)"},{"frequency":"1369","word":"mort","type":"(adj.)"},{"frequency":"1368","word":"jeunesse","type":"(subst.)"},{"frequency":"1367","word":"bureau","type":"(subst.)"},{"frequency":"1367","word":"sac","type":"(subst.)"},{"frequency":"1366","word":"&eacute;tranger","type":"(adj.)"},{"frequency":"1363","word":"courage","type":"(subst.)"},{"frequency":"1363","word":"souffler","type":"(verbe)"},{"frequency":"1360","word":"jaune","type":"(adj.)"},{"frequency":"1360","word":"page","type":"(subst.)"},{"frequency":"1359","word":"&eacute;tranger","type":"(subst.)"},{"frequency":"1356","word":"etc","type":"(adv.)"},{"frequency":"1353","word":"miser","type":"(subst.)"},{"frequency":"1352","word":"pass&eacute;","type":"(subst.)"},{"frequency":"1351","word":"rapide","type":"(adj.)"},{"frequency":"1350","word":"digne","type":"(adj.)"},{"frequency":"1349","word":"chaud","type":"(adj.)"},{"frequency":"1349","word":"propos","type":"(subst.)"},{"frequency":"1348","word":"attirer","type":"(verbe)"},{"frequency":"1344","word":"pr&ecirc;ter","type":"(verbe)"},{"frequency":"1336","word":"clair","type":"(adj.)"},{"frequency":"1329","word":"amuser","type":"(verbe)"},{"frequency":"1327","word":"occasion","type":"(subst.)"},{"frequency":"1325","word":"voile","type":"(subst.)"},{"frequency":"1323","word":"&eacute;clater","type":"(verbe)"},{"frequency":"1322","word":"importance","type":"(subst)"},{"frequency":"1322","word":"quartier","type":"(subst.)"},{"frequency":"1322","word":"soi","type":"(pron.)"},{"frequency":"1318","word":"auteur","type":"(subst.)"},{"frequency":"1316","word":"religion","type":"(subst.)"},{"frequency":"1314","word":"palais","type":"(subst.)"},{"frequency":"1314","word":"r&eacute;unir","type":"(verbe)"},{"frequency":"1310","word":"traiter","type":"(verbe)"},{"frequency":"1309","word":"flot","type":"(subst.)"},{"frequency":"1309","word":"intelligence","type":"(subst.)"},{"frequency":"1307","word":"tant&ocirc;t","type":"(adv.)"},{"frequency":"1307","word":"voisin","type":"(subst.)"},{"frequency":"1305","word":"carte","type":"(subst.)"},{"frequency":"1301","word":"secret","type":"(adj.)"},{"frequency":"1296","word":"animal","type":"(subst.)"},{"frequency":"1293","word":"&eacute;t&eacute;","type":"(subst.)"},{"frequency":"1293","word":"tra&icirc;ner","type":"(verbe)"},{"frequency":"1292","word":"cabinet","type":"(subst.)"},{"frequency":"1292","word":"morceau","type":"(subst.)"},{"frequency":"1290","word":"employer","type":"(verbe)"},{"frequency":"1287","word":"capable","type":"(adj.)"},{"frequency":"1286","word":"souffrance","type":"(subst)"},{"frequency":"1285","word":"marquer","type":"(verbe)"},{"frequency":"1285","word":"prouver","type":"(verbe)"},{"frequency":"1284","word":"importer","type":"(verbe)"},{"frequency":"1284","word":"titre","type":"(subst.)"},{"frequency":"1282","word":"d&eacute;sert","type":"(subst.)"},{"frequency":"1280","word":"facile","type":"(adj.)"},{"frequency":"1280","word":"spectacle","type":"(subst.)"},{"frequency":"1279","word":"exiger","type":"(verbe)"},{"frequency":"1277","word":"reposer","type":"(verbe)"},{"frequency":"1276","word":"d&eacute;part","type":"(subst.)"},{"frequency":"1276","word":"fier","type":"(adj.)"},{"frequency":"1275","word":"danser","type":"(verbe)"},{"frequency":"1268","word":"demande","type":"(subst.)"},{"frequency":"1268","word":"saluer","type":"(verbe)"},{"frequency":"1267","word":"lueur","type":"(subst.)"},{"frequency":"1266","word":"joue","type":"(subst.)"},{"frequency":"1265","word":"saint","type":"(adj.)"},{"frequency":"1264","word":"accorder","type":"(verbe)"},{"frequency":"1264","word":"pri&egrave;re","type":"(subst.)"},{"frequency":"1262","word":"achever","type":"(verbe)"},{"frequency":"1262","word":"avouer","type":"(verbe)"},{"frequency":"1261","word":"distinguer","type":"(verbe)"},{"frequency":"1261","word":"emmener","type":"(verbe)"},{"frequency":"1260","word":"fonction","type":"(subst.)"},{"frequency":"1256","word":"durant","type":"(pr&eacute;p.)"},{"frequency":"1253","word":"haut","type":"(adv.)"},{"frequency":"1251","word":"aspect","type":"(subst.)"},{"frequency":"1251","word":"sommeil","type":"(subst.)"},{"frequency":"1249","word":"&eacute;clat","type":"(subst.)"},{"frequency":"1248","word":"moiti&eacute;","type":"(subst.)"},{"frequency":"1247","word":"demi","type":"(adj.)"},{"frequency":"1246","word":"calme","type":"(adj.)"},{"frequency":"1244","word":"contraire","type":"(subst.)"},{"frequency":"1239","word":"colline","type":"(subst.)"},{"frequency":"1238","word":"agiter","type":"(verbe)"},{"frequency":"1232","word":"h&eacute;siter","type":"(verbe)"},{"frequency":"1223","word":"terrain","type":"(subst.)"},{"frequency":"1222","word":"rare","type":"(adj.)"},{"frequency":"1221","word":"poids","type":"(subst.)"},{"frequency":"1221","word":"sonner","type":"(verbe)"},{"frequency":"1219","word":"changement","type":"(subst)"},{"frequency":"1218","word":"charge","type":"(subst.)"},{"frequency":"1218","word":"davantage","type":"(adv.)"},{"frequency":"1217","word":"composer","type":"(verbe)"},{"frequency":"1215","word":"enlever","type":"(verbe)"},{"frequency":"1211","word":"poche","type":"(subst.)"},{"frequency":"1210","word":"rejoindre","type":"(verbe)"},{"frequency":"1208","word":"son","type":"(subst.)"},{"frequency":"1205","word":"int&eacute;rieur","type":"(adj.)"},{"frequency":"1204","word":"veille","type":"(subst.)"},{"frequency":"1203","word":"ramener","type":"(verbe)"},{"frequency":"1200","word":"fruit","type":"(subst.)"},{"frequency":"1199","word":"complet","type":"(adj.)"},{"frequency":"1199","word":"&eacute;tudier","type":"(verbe)"},{"frequency":"1198","word":"partager","type":"(verbe)"},{"frequency":"1192","word":"croix","type":"(subst.)"},{"frequency":"1191","word":"suivant","type":"(adj.)"},{"frequency":"1187","word":"chasser","type":"(verbe)"},{"frequency":"1186","word":"interrompre","type":"(verb)"},{"frequency":"1185","word":"&eacute;loigner","type":"(verbe)"},{"frequency":"1185","word":"tr&eacute;sor","type":"(subst.)"},{"frequency":"1184","word":"compagnie","type":"(subst.)"},{"frequency":"1181","word":"&eacute;troit","type":"(adj.)"},{"frequency":"1180","word":"cuisine","type":"(subst.)"},{"frequency":"1177","word":"r&eacute;duire","type":"(verbe)"},{"frequency":"1309","word":"engager","type":"(verbe)"},{"frequency":"1175","word":"&eacute;gal","type":"(adj.)"},{"frequency":"1174","word":"empire","type":"(subst.)"},{"frequency":"1170","word":"nation","type":"(subst.)"},{"frequency":"1169","word":"&eacute;teindre","type":"(verbe)"},{"frequency":"1169","word":"recommencer","type":"(verb)"},{"frequency":"1169","word":"sauter","type":"(verbe)"},{"frequency":"1168","word":"plaindre","type":"(verbe)"},{"frequency":"1167","word":"conversation","type":"(subst.)"},{"frequency":"1166","word":"soir&eacute;e","type":"(subst.)"},{"frequency":"1166","word":"violent","type":"(adj.)"},{"frequency":"1164","word":"impression","type":"(subst)"},{"frequency":"1164","word":"trait","type":"(subst.)"},{"frequency":"1163","word":"devant","type":"(adv.)"},{"frequency":"1162","word":"pr&eacute;f&eacute;rer","type":"(verbe)"},{"frequency":"1162","word":"r&eacute;v&eacute;ler","type":"(verbe)"},{"frequency":"1162","word":"sien","type":"(pron.)"},{"frequency":"1156","word":"magnifique","type":"(adj.)"},{"frequency":"1154","word":"d&eacute;sespoir","type":"(subst.)"},{"frequency":"1153","word":"t&eacute;moin","type":"(subst.)"},{"frequency":"1152","word":"visite","type":"(subst.)"},{"frequency":"1148","word":"respect","type":"(subst.)"},{"frequency":"1142","word":"solitude","type":"(subst.)"},{"frequency":"1140","word":"subir","type":"(verbe)"},{"frequency":"1136","word":"del&agrave;","type":"(adv.)"},{"frequency":"1136","word":"prochain","type":"(adj.)"},{"frequency":"1135","word":"anglais","type":"(subst.)"},{"frequency":"1135","word":"rapporter","type":"(verbe)"},{"frequency":"1128","word":"co&ucirc;ter","type":"(verbe)"},{"frequency":"1128","word":"r&eacute;fl&eacute;chir","type":"(verbe)"},{"frequency":"1127","word":"officier","type":"(subst.)"},{"frequency":"1127","word":"remercier","type":"(verbe)"},{"frequency":"1126","word":"d&eacute;poser","type":"(verbe)"},{"frequency":"1125","word":"fauteuil","type":"(subst.)"},{"frequency":"1124","word":"fumer","type":"(verbe)"},{"frequency":"1124","word":"t&ocirc;t","type":"(adv.)"},{"frequency":"1119","word":"affirmer","type":"(verbe)"},{"frequency":"1118","word":"relation","type":"(subst.)"},{"frequency":"1117","word":"fum&eacute;e","type":"(subst.)"},{"frequency":"1116","word":"convenir","type":"(verbe)"},{"frequency":"1115","word":"branche","type":"(subst.)"},{"frequency":"1115","word":"malade","type":"(adj.)"},{"frequency":"1113","word":"circonstance","type":"(subst.)"},{"frequency":"1113","word":"ouvrage","type":"(subst.)"},{"frequency":"1108","word":"compagnon","type":"(subst.)"},{"frequency":"1108","word":"v&ecirc;tir","type":"(verbe)"},{"frequency":"1106","word":"exp&eacute;rience","type":"(subst.)"},{"frequency":"1106","word":"port","type":"(subst.)"},{"frequency":"1105","word":"accomplir","type":"(verbe)"},{"frequency":"1105","word":"avec","type":"(adv.)"},{"frequency":"1103","word":"r&eacute;soudre","type":"(verbe)"},{"frequency":"1100","word":"plonger","type":"(verbe)"},{"frequency":"1099","word":"goutte","type":"(subst.)"},{"frequency":"1099","word":"mien","type":"(pron.)"},{"frequency":"1098","word":"chant","type":"(subst.)"},{"frequency":"1095","word":"d&eacute;truire","type":"(verbe)"},{"frequency":"1087","word":"combat","type":"(subst.)"},{"frequency":"1086","word":"personnage","type":"(subst.)"},{"frequency":"1085","word":"aventure","type":"(subst.)"},{"frequency":"1085","word":"int&eacute;resser","type":"(verbe)"},{"frequency":"1084","word":"disposer","type":"(verbe)"},{"frequency":"1081","word":"absence","type":"(subst.)"},{"frequency":"1079","word":"machine","type":"(subst.)"},{"frequency":"1078","word":"aucun","type":"(pron.)"},{"frequency":"1078","word":"gr&acirc;ce","type":"(pr&eacute;p.)"},{"frequency":"1077","word":"cha&icirc;ne","type":"(subst.)"},{"frequency":"1076","word":"honte","type":"(subst.)"},{"frequency":"1075","word":"fait","type":"(adj.)"},{"frequency":"1075","word":"lisser","type":"(verbe)"},{"frequency":"1072","word":"faim","type":"(subst.)"},{"frequency":"1072","word":"plaine","type":"(subst.)"},{"frequency":"1071","word":"verser","type":"(verbe)"},{"frequency":"1066","word":"pointe","type":"(subst.)"},{"frequency":"1065","word":"ob&eacute;ir","type":"(verbe)"},{"frequency":"1065","word":"preuve","type":"(subst.)"},{"frequency":"1063","word":"&eacute;ternel","type":"(adj.)"},{"frequency":"1062","word":"lutter","type":"(verbe)"},{"frequency":"1061","word":"pr&eacute;tendre","type":"(verbe)"},{"frequency":"1060","word":"bataille","type":"(subst.)"},{"frequency":"1060","word":"construire","type":"(verbe)"},{"frequency":"1060","word":"&eacute;nergie","type":"(subst.)"},{"frequency":"1055","word":"victime","type":"(subst.)"},{"frequency":"1053","word":"sauvage","type":"(adj.)"},{"frequency":"1052","word":"soumettre","type":"(verbe)"},{"frequency":"1052","word":"usage","type":"(subst.)"},{"frequency":"1050","word":"peser","type":"(verbe)"},{"frequency":"1046","word":"double","type":"(adj.)"},{"frequency":"1045","word":"tache","type":"(subst.)"},{"frequency":"1044","word":"gu&egrave;re","type":"(adv.)"},{"frequency":"1043","word":"hauteur","type":"(subst.)"},{"frequency":"1043","word":"troubler","type":"(verbe)"},{"frequency":"1039","word":"tendre","type":"(adj.)"},{"frequency":"1037","word":"beau","type":"(subst.)"},{"frequency":"1037","word":"curiosit&eacute;","type":"(subst.)"},{"frequency":"1032","word":"r&eacute;pandre","type":"(verbe)"},{"frequency":"1031","word":"glace","type":"(subst.)"},{"frequency":"1031","word":"r&eacute;sister","type":"(verbe)"},{"frequency":"1027","word":"froid","type":"(subst.)"},{"frequency":"1024","word":"prison","type":"(subst.)"},{"frequency":"1023","word":"&eacute;tage","type":"(subst.)"},{"frequency":"1022","word":"billet","type":"(subst.)"},{"frequency":"1022","word":"droit","type":"(adj.)"},{"frequency":"1022","word":"s&eacute;rieux","type":"(adj.)"},{"frequency":"1021","word":"prot&eacute;ger","type":"(verbe)"},{"frequency":"1019","word":"pauvre","type":"(subst.)"},{"frequency":"1019","word":"rose","type":"(subst.)"},{"frequency":"1016","word":"enfermer","type":"(verbe)"},{"frequency":"1014","word":"attitude","type":"(subst.)"},{"frequency":"1014","word":"dur","type":"(adj.)"},{"frequency":"1012","word":"mode","type":"(subst.)"},{"frequency":"1010","word":"neuf","type":"(adj.)"},{"frequency":"1006","word":"crainte","type":"(subst.)"},{"frequency":"1006","word":"creuser","type":"(verbe)"},{"frequency":"1006","word":"grandir","type":"(verbe)"},{"frequency":"1004","word":"enfoncer","type":"(verbe)"},{"frequency":"1003","word":"v&ecirc;tement","type":"(subst.)"},{"frequency":"1001","word":"envelopper","type":"(verbe)"},{"frequency":"1000","word":"vague","type":"(adj.)"},{"frequency":"999","word":"pr&eacute;venir","type":"(verbe)"},{"frequency":"998","word":"violence","type":"(subst.)"},{"frequency":"996","word":"inspirer","type":"(verbe)"},{"frequency":"993","word":"inutile","type":"(adj.)"},{"frequency":"992","word":"content","type":"(adj.)"},{"frequency":"992","word":"courant","type":"(subst.)"},{"frequency":"992","word":"folie","type":"(subst.)"},{"frequency":"992","word":"piti&eacute;","type":"(subst.)"},{"frequency":"988","word":"intention","type":"(subst.)"},{"frequency":"988","word":"ramasser","type":"(verbe)"},{"frequency":"987","word":"endormir","type":"(verbe)"},{"frequency":"986","word":"inventer","type":"(verbe)"},{"frequency":"985","word":"trace","type":"(subst.)"},{"frequency":"980","word":"toile","type":"(subst.)"},{"frequency":"977","word":"presser","type":"(verbe)"},{"frequency":"976","word":"confier","type":"(verbe)"},{"frequency":"976","word":"effacer","type":"(verbe)"},{"frequency":"973","word":"reculer","type":"(verbe)"},{"frequency":"973","word":"user","type":"(verbe)"},{"frequency":"972","word":"blanc","type":"(subst.)"},{"frequency":"971","word":"nourrir","type":"(verbe)"},{"frequency":"970","word":"dangereux","type":"(adj.)"},{"frequency":"967","word":"po&eacute;sie","type":"(subst.)"},{"frequency":"962","word":"sommet","type":"(subst.)"},{"frequency":"961","word":"remplacer","type":"(verbe)"},{"frequency":"960","word":"souhaiter","type":"(verbe)"},{"frequency":"956","word":"avance","type":"(subst.)"},{"frequency":"955","word":"autorit&eacute;","type":"(subst.)"},{"frequency":"954","word":"&eacute;pais","type":"(adj.)"},{"frequency":"953","word":"inqui&eacute;tude","type":"(subst.)"},{"frequency":"952","word":"choix","type":"(subst.)"},{"frequency":"951","word":"tombe","type":"(subst.)"},{"frequency":"950","word":"marchand","type":"(subst.)"},{"frequency":"949","word":"nombreux","type":"(adj.)"},{"frequency":"948","word":"muet","type":"(adj.)"},{"frequency":"947","word":"signer","type":"(verbe)"},{"frequency":"946","word":"absolument","type":"(adv.)"},{"frequency":"944","word":"cercle","type":"(subst.)"},{"frequency":"944","word":"interroger","type":"(verbe)"},{"frequency":"942","word":"dominer","type":"(verbe)"},{"frequency":"940","word":"d&eacute;faut","type":"(subst.)"},{"frequency":"938","word":"enfance","type":"(subst.)"},{"frequency":"937","word":"faveur","type":"(subst.)"},{"frequency":"937","word":"r&eacute;el","type":"(adj.)"},{"frequency":"934","word":"commander","type":"(verbe)"},{"frequency":"934","word":"supposer","type":"(verbe)"},{"frequency":"933","word":"d&eacute;passer","type":"(verbe)"},{"frequency":"930","word":"sourd","type":"(adj.)"},{"frequency":"929","word":"cruel","type":"(adj.)"},{"frequency":"928","word":"dimanche","type":"(subst.)"},{"frequency":"928","word":"erreur","type":"(subst.)"},{"frequency":"927","word":"cerveau","type":"(subst.)"},{"frequency":"926","word":"accuser","type":"(verbe)"},{"frequency":"924","word":"arriv&eacute;e","type":"(subst.)"},{"frequency":"924","word":"rapidement","type":"(adv.)"},{"frequency":"922","word":"vol","type":"(subst.)"},{"frequency":"921","word":"habiller","type":"(verbe)"},{"frequency":"920","word":"condamner","type":"(verbe)"},{"frequency":"918","word":"lors","type":"(adv.)"},{"frequency":"918","word":"menacer","type":"(verbe)"},{"frequency":"918","word":"seuil","type":"(subst.)"},{"frequency":"916","word":"&eacute;craser","type":"(verbe)"},{"frequency":"915","word":"perte","type":"(subst.)"},{"frequency":"914","word":"troisi&egrave;me","type":"(adj.)"},{"frequency":"913","word":"chance","type":"(subst.)"},{"frequency":"906","word":"vieil","type":"(adj.)"},{"frequency":"905","word":"m&ecirc;me","type":"(pron.)"},{"frequency":"902","word":"c&eacute;der","type":"(verbe)"},{"frequency":"901","word":"douceur","type":"(subst.)"},{"frequency":"901","word":"droite","type":"(adj.)"},{"frequency":"900","word":"vide","type":"(subst.)"},{"frequency":"899","word":"autrement","type":"(adv.)"},{"frequency":"899","word":"dr&ocirc;le","type":"(adj.)"},{"frequency":"899","word":"ruine","type":"(subst.)"},{"frequency":"898","word":"&eacute;carter","type":"(verbe)"},{"frequency":"898","word":"rang","type":"(subst.)"},{"frequency":"897","word":"r&eacute;clamer","type":"(verbe)"},{"frequency":"896","word":"chiffre","type":"(subst.)"},{"frequency":"892","word":"voisin","type":"(adj.)"},{"frequency":"890","word":"militaire","type":"(adj.)"},{"frequency":"884","word":"roche","type":"(subst.)"},{"frequency":"883","word":"distance","type":"(subst.)"},{"frequency":"882","word":"apparence","type":"(subst.)"},{"frequency":"881","word":"dessiner","type":"(verbe)"},{"frequency":"877","word":"conclure","type":"(verbe)"},{"frequency":"877","word":"fran&ccedil;ois","type":"(subst.)"},{"frequency":"877","word":"lier","type":"(verbe)"},{"frequency":"876","word":"discussion","type":"(subst)"},{"frequency":"873","word":"admettre","type":"(verbe)"},{"frequency":"873","word":"banc","type":"(subst.)"},{"frequency":"873","word":"terreur","type":"(subst.)"},{"frequency":"872","word":"attaquer","type":"(verbe)"},{"frequency":"872","word":"vers","type":"(subst.)"},{"frequency":"871","word":"respecter","type":"(verbe)"},{"frequency":"869","word":"rose","type":"(adj.)"},{"frequency":"869","word":"silencieux","type":"(adj.)"},{"frequency":"868","word":"anglais","type":"(adj.)"},{"frequency":"868","word":"course","type":"(subst.)"},{"frequency":"865","word":"portier","type":"(subst.)"},{"frequency":"861","word":"chat","type":"(subst.)"},{"frequency":"860","word":"pendre","type":"(verbe)"},{"frequency":"859","word":"supporter","type":"(verbe)"},{"frequency":"856","word":"temp&ecirc;te","type":"(subst.)"},{"frequency":"855","word":"parfaitement","type":"(adv)"},{"frequency":"855","word":"paysage","type":"(subst.)"},{"frequency":"855","word":"quart","type":"(subst.)"},{"frequency":"853","word":"figurer","type":"(verbe)"},{"frequency":"851","word":"profiter","type":"(verbe)"},{"frequency":"847","word":"accrocher","type":"(verbe)"},{"frequency":"843","word":"calmer","type":"(verbe)"},{"frequency":"843","word":"satisfaire","type":"(verbe)"},{"frequency":"842","word":"public","type":"(subst.)"},{"frequency":"838","word":"race","type":"(subst.)"},{"frequency":"838","word":"valoir","type":"(verbe)"},{"frequency":"837","word":"barbe","type":"(subst.)"},{"frequency":"836","word":"signifier","type":"(verbe)"},{"frequency":"835","word":"couche","type":"(subst.)"},{"frequency":"834","word":"inqui&eacute;ter","type":"(verbe)"},{"frequency":"833","word":"colon","type":"(subst.)"},{"frequency":"833","word":"d&eacute;sormais","type":"(adv.)"},{"frequency":"831","word":"fid&egrave;le","type":"(adj.)"},{"frequency":"829","word":"assister","type":"(verbe)"},{"frequency":"829","word":"rideau","type":"(subst.)"},{"frequency":"828","word":"inviter","type":"(verbe)"},{"frequency":"827","word":"d&eacute;chirer","type":"(verbe)"},{"frequency":"824","word":"fatigue","type":"(subst.)"},{"frequency":"824","word":"risquer","type":"(verbe)"},{"frequency":"823","word":"r&egrave;gle","type":"(subst.)"},{"frequency":"822","word":"gauche","type":"(adj.)"},{"frequency":"822","word":"parcourir","type":"(verbe)"},{"frequency":"822","word":"pr&eacute;sent","type":"(adj.)"},{"frequency":"821","word":"rejeter","type":"(verbe)"},{"frequency":"820","word":"naissance","type":"(subst.)"},{"frequency":"818","word":"loup","type":"(subst.)"},{"frequency":"816","word":"renoncer","type":"(verbe)"},{"frequency":"815","word":"compl&egrave;tement","type":"(adv)"},{"frequency":"814","word":"extraordinaire","type":"(adj.)"},{"frequency":"810","word":"veiller","type":"(verbe)"},{"frequency":"806","word":"transformer","type":"(verb)"},{"frequency":"805","word":"tracer","type":"(verbe)"},{"frequency":"804","word":"chute","type":"(subst.)"},{"frequency":"803","word":"divers","type":"(adj.)"},{"frequency":"802","word":"r&eacute;sistance","type":"(subst)"},{"frequency":"801","word":"contenter","type":"(verbe)"},{"frequency":"800","word":"chemise","type":"(subst.)"},{"frequency":"800","word":"mince","type":"(adj.)"},{"frequency":"800","word":"naturellement","type":"(adv.)"},{"frequency":"799","word":"si&egrave;ge","type":"(subst.)"},{"frequency":"797","word":"as","type":"(subst.)"},{"frequency":"797","word":"patron","type":"(subst.)"},{"frequency":"796","word":"calme","type":"(subst.)"},{"frequency":"795","word":"m&eacute;riter","type":"(verbe)"},{"frequency":"795","word":"printemps","type":"(subst.)"},{"frequency":"793","word":"angoisse","type":"(subst.)"},{"frequency":"791","word":"pr&eacute;cipiter","type":"(verbe)"},{"frequency":"791","word":"rompre","type":"(verbe)"},{"frequency":"788","word":"habitant","type":"(subst.)"},{"frequency":"788","word":"plein","type":"(pr&eacute;p.)"},{"frequency":"784","word":"caresser","type":"(verbe)"},{"frequency":"784","word":"m&eacute;tier","type":"(subst.)"},{"frequency":"783","word":"&eacute;touffer","type":"(verbe)"},{"frequency":"782","word":"animer","type":"(verbe)"},{"frequency":"782","word":"note","type":"(subst.)"},{"frequency":"781","word":"pass&eacute;","type":"(adj.)"},{"frequency":"779","word":"fine","type":"(adj.)"},{"frequency":"779","word":"fixe","type":"(adj.)"},{"frequency":"778","word":"casser","type":"(verbe)"},{"frequency":"777","word":"fusil","type":"(subst.)"},{"frequency":"774","word":"rond","type":"(adj.)"},{"frequency":"771","word":"agent","type":"(subst.)"},{"frequency":"763","word":"fonder","type":"(verbe)"},{"frequency":"760","word":"roman","type":"(subst.)"},{"frequency":"759","word":"franchir","type":"(verbe)"},{"frequency":"759","word":"plante","type":"(subst.)"},{"frequency":"754","word":"abattre","type":"(verbe)"},{"frequency":"754","word":"discuter","type":"(verbe)"},{"frequency":"748","word":"fatiguer","type":"(verbe)"},{"frequency":"746","word":"humide","type":"(adj.)"},{"frequency":"746","word":"r&eacute;flexion","type":"(subst.)"},{"frequency":"745","word":"consentir","type":"(verbe)"},{"frequency":"740","word":"accent","type":"(subst.)"},{"frequency":"738","word":"curieux","type":"(adj.)"},{"frequency":"735","word":"repas","type":"(subst.)"},{"frequency":"731","word":"&eacute;tendue","type":"(subst.)"},{"frequency":"731","word":"regretter","type":"(verbe)"},{"frequency":"730","word":"joindre","type":"(verbe)"},{"frequency":"730","word":"profond&eacute;ment","type":"(adv)"},{"frequency":"729","word":"secours","type":"(subst.)"},{"frequency":"728","word":"commencement","type":"(subst.)"},{"frequency":"724","word":"corde","type":"(subst.)"},{"frequency":"720","word":"secr&eacute;taire","type":"(subst)"},{"frequency":"720","word":"vaincre","type":"(verbe)"},{"frequency":"718","word":"saison","type":"(subst.)"},{"frequency":"715","word":"pr&eacute;cieux","type":"(adj.)"},{"frequency":"714","word":"pr&eacute;cis","type":"(adj.)"},{"frequency":"712","word":"consulter","type":"(verbe)"},{"frequency":"709","word":"ha&iuml;r","type":"(verbe)"},{"frequency":"701","word":"repousser","type":"(verbe)"},{"frequency":"700","word":"paupi&egrave;re","type":"(subst.)"},{"frequency":"696","word":"certainement","type":"(adv)"},{"frequency":"695","word":"tapis","type":"(subst.)"},{"frequency":"694","word":"noire","type":"(adj.)"},{"frequency":"691","word":"chasse","type":"(subst.)"},{"frequency":"690","word":"ex&eacute;cuter","type":"(verbe)"},{"frequency":"690","word":"nerveux","type":"(adj.)"},{"frequency":"690","word":"nul","type":"(d&eacute;t.)"},{"frequency":"689","word":"commun","type":"(adj.)"},{"frequency":"689","word":"exposer","type":"(verbe)"},{"frequency":"686","word":"clef","type":"(subst.)"},{"frequency":"684","word":"claire","type":"(adj.)"},{"frequency":"683","word":"voyager","type":"(verbe)"},{"frequency":"680","word":"haute","type":"(adj.)"},{"frequency":"680","word":"renverser","type":"(verbe)"},{"frequency":"677","word":"sueur","type":"(subst.)"},{"frequency":"676","word":"&acirc;g&eacute;","type":"(adj.)"},{"frequency":"675","word":"ferme","type":"(subst.)"},{"frequency":"675","word":"rassurer","type":"(verbe)"},{"frequency":"674","word":"retomber","type":"(verbe)"},{"frequency":"672","word":"d&eacute;crire","type":"(verbe)"},{"frequency":"670","word":"mentir","type":"(verbe)"},{"frequency":"669","word":"instinct","type":"(subst.)"},{"frequency":"667","word":"armer","type":"(verbe)"},{"frequency":"667","word":"paquet","type":"(subst.)"},{"frequency":"666","word":"drame","type":"(subst.)"},{"frequency":"664","word":"absolu","type":"(adj.)"},{"frequency":"661","word":"savoir","type":"(subst.)"},{"frequency":"660","word":"mine","type":"(subst.)"},{"frequency":"660","word":"vision","type":"(subst.)"},{"frequency":"659","word":"&eacute;taler","type":"(verbe)"},{"frequency":"658","word":"sentier","type":"(subst.)"},{"frequency":"657","word":"demain","type":"(subst.)"},{"frequency":"655","word":"beau","type":"(adv.)"},{"frequency":"652","word":"blond","type":"(adj.)"},{"frequency":"651","word":"essuyer","type":"(verbe)"},{"frequency":"650","word":"planche","type":"(subst.)"},{"frequency":"650","word":"pr&eacute;c&eacute;der","type":"(verbe)"},{"frequency":"649","word":"dehors","type":"(subst.)"},{"frequency":"647","word":"salut","type":"(subst.)"},{"frequency":"646","word":"t&acirc;che","type":"(subst.)"},{"frequency":"644","word":"d&eacute;signer","type":"(verbe)"},{"frequency":"643","word":"fin","type":"(adj.)"},{"frequency":"642","word":"abri","type":"(subst.)"},{"frequency":"641","word":"d&eacute;tacher","type":"(verbe)"},{"frequency":"638","word":"recueillir","type":"(verbe)"},{"frequency":"636","word":"rencontre","type":"(subst.)"},{"frequency":"634","word":"croiser","type":"(verbe)"},{"frequency":"633","word":"entretenir","type":"(verbe)"},{"frequency":"633","word":"rouge","type":"(subst.)"},{"frequency":"627","word":"professeur","type":"(subst)"},{"frequency":"627","word":"surveiller","type":"(verbe)"},{"frequency":"627","word":"visible","type":"(adj.)"},{"frequency":"625","word":"perdu","type":"(adj.)"},{"frequency":"622","word":"r&eacute;server","type":"(verbe)"},{"frequency":"620","word":"bas","type":"(adv.)"},{"frequency":"618","word":"lien","type":"(subst.)"},{"frequency":"615","word":"queue","type":"(subst.)"},{"frequency":"608","word":"bande","type":"(subst.)"},{"frequency":"608","word":"confondre","type":"(verbe)"},{"frequency":"605","word":"grain","type":"(subst.)"},{"frequency":"603","word":"mensonge","type":"(subst.)"},{"frequency":"602","word":"d&eacute;gager","type":"(verbe)"},{"frequency":"592","word":"probablement","type":"(adv)"},{"frequency":"591","word":"illusion","type":"(subst.)"},{"frequency":"589","word":"incapable","type":"(adj.)"},{"frequency":"589","word":"parer","type":"(verbe)"},{"frequency":"586","word":"&eacute;preuve","type":"(subst.)"},{"frequency":"581","word":"imm&eacute;diatement","type":"(adv)"},{"frequency":"578","word":"attente","type":"(subst.)"},{"frequency":"572","word":"visiter","type":"(verbe)"},{"frequency":"571","word":"instrument","type":"(subst)"},{"frequency":"569","word":"&eacute;videmment","type":"(adv.)"},{"frequency":"556","word":"auparavant","type":"(adv.)"},{"frequency":"554","word":"d&eacute;tourner","type":"(verbe)"},{"frequency":"553","word":"explication","type":"(subs)"},{"frequency":"551","word":"r&eacute;gulier","type":"(adj.)"},{"frequency":"549","word":"reproche","type":"(subst.)"},{"frequency":"547","word":"souci","type":"(subst.)"},{"frequency":"546","word":"plier","type":"(verbe)"},{"frequency":"544","word":"extr&ecirc;me","type":"(adj.)"},{"frequency":"540","word":"accueillir","type":"(verbe)"},{"frequency":"538","word":"juif","type":"(subst.)"},{"frequency":"538","word":"le&ccedil;on","type":"(subst.)"},{"frequency":"538","word":"redevenir","type":"(verbe)"},{"frequency":"537","word":"approuver","type":"(verbe)"},{"frequency":"536","word":"parfait","type":"(adj.)"},{"frequency":"535","word":"emparer","type":"(verbe)"},{"frequency":"532","word":"aborder","type":"(verbe)"},{"frequency":"529","word":"heurter","type":"(verbe)"},{"frequency":"523","word":"tel","type":"(pron.)"},{"frequency":"519","word":"noyer","type":"(verbe)"},{"frequency":"515","word":"semer","type":"(verbe)"},{"frequency":"514","word":"ferme","type":"(adj.)"},{"frequency":"494","word":"manche","type":"(subst.)"},{"frequency":"492","word":"rage","type":"(subst.)"},{"frequency":"491","word":"gr&eacute;","type":"(subst.)"},{"frequency":"450","word":"guider","type":"(verbe)"},{"frequency":"449","word":"piquer","type":"(verbe)"},{"frequency":"412","word":"meilleur","type":"(subst.)"}]